{
  "$schema": "https://static.modelcontextprotocol.io/schemas/2025-12-11/server.schema.json",
  "name": "io.github.devag7/linkedin-mcp",
  "description": "LinkedIn for AI assistants — profiles, people/job/company search, feed and messaging as structured JSON, plus gated writes (connect/message/post/react/comment) via LinkedIn's API instead of DOM-clicking. Stealth-browser engine that passes Cloudflare; built-in safety layer.",
  "repository": {
    "url": "https://github.com/devag7/linkedin-mcp",
    "source": "github"
  },
  "version": "2.0.2",
  "packages": [
    {
      "registryType": "npm",
      "identifier": "linkedin-mcp-tools",
      "version": "2.0.2",
      "transport": {
        "type": "stdio"
      }
    }
  ]
}
